{"place_id":399864815,"licence":"Data © OpenStreetMap contributors, ODbL 1.0. http://osm.org/copyright","osm_type":"node","osm_id":12599810937,"lat":"35.6889533","lon":"139.7286142","category":"office","type":"coworking","place_rank":30,"importance":8.593499656667457e-05,"addresstype":"office","name":"Tokyo Bitcoin Base","display_name":"Tokyo Bitcoin Base, 外堀通り, 四谷本塩町, 四谷, 新宿区, 東京都, 160-8484, 日本","address":{"office":"Tokyo Bitcoin Base","road":"外堀通り","neighbourhood":"四谷本塩町","suburb":"四谷","city":"新宿区","ISO3166-2-lvl4":"JP-13","postcode":"160-8484","country":"日本","country_code":"jp"},"boundingbox":["35.6889033","35.6890033","139.7285642","139.7286642"]}