{"place_id":287312018,"licence":"Data © OpenStreetMap contributors, ODbL 1.0. http://osm.org/copyright","osm_type":"way","osm_id":399289735,"lat":"13.7207002","lon":"-89.1695166","category":"amenity","type":"fast_food","place_rank":30,"importance":6.725185015635947e-05,"addresstype":"amenity","name":"Don Pollo","display_name":"Don Pollo, Avenida Paleca, Barrio El Calvario, Colonia Acolhuatán, Ciudad Delgado, San Salvador Centro, San Salvador, 1118, El Salvador","address":{"amenity":"Don Pollo","road":"Avenida Paleca","suburb":"Barrio El Calvario","village":"Colonia Acolhuatán","town":"Ciudad Delgado","municipality":"San Salvador Centro","state":"San Salvador","ISO3166-2-lvl4":"SV-SS","postcode":"1118","country":"El Salvador","country_code":"sv"},"boundingbox":["13.7206556","13.7207426","-89.1696088","-89.1694241"]}