{"place_id":396716888,"licence":"Data © OpenStreetMap contributors, ODbL 1.0. http://osm.org/copyright","osm_type":"node","osm_id":12497451991,"lat":"13.6110919","lon":"100.6377345","category":"shop","type":"hairdresser","place_rank":30,"importance":5.000152590214416e-05,"addresstype":"shop","name":"Pooky & Team Salon","display_name":"Pooky & Team Salon, 99/234, Soi Si Charoen Villa, ศรีเจริญวิลล่า, บ้านบางปิ้ง, ตำบลบางเมือง, เทศบาลเมืองปากน้ำสมุทรปราการ, อำเภอเมืองสมุทรปราการ, จังหวัดสมุทรปราการ, 10270, ประเทศไทย","address":{"shop":"Pooky & Team Salon","house_number":"99/234","road":"Soi Si Charoen Villa","residential":"ศรีเจริญวิลล่า","village":"บ้านบางปิ้ง","city":"ตำบลบางเมือง","municipality":"เทศบาลเมืองปากน้ำสมุทรปราการ","county":"อำเภอเมืองสมุทรปราการ","province":"จังหวัดสมุทรปราการ","ISO3166-2-lvl4":"TH-11","postcode":"10270","country":"ประเทศไทย","country_code":"th"},"boundingbox":["13.6110419","13.6111419","100.6376845","100.6377845"]}