{"place_id":390879177,"licence":"Data © OpenStreetMap contributors, ODbL 1.0. http://osm.org/copyright","osm_type":"node","osm_id":12393086957,"lat":"13.7112104","lon":"-89.2076687","category":"shop","type":"variety_store","place_rank":30,"importance":6.725185015635947e-05,"addresstype":"shop","name":"Dollarcity","display_name":"Dollarcity, SAL91N, Condominio 2000, Distrito Municipal 2, San Salvador, San Salvador Centro, San Salvador, 1102, El Salvador","address":{"shop":"Dollarcity","road":"SAL91N","neighbourhood":"Condominio 2000","city_district":"Distrito Municipal 2","city":"San Salvador","municipality":"San Salvador Centro","state":"San Salvador","ISO3166-2-lvl4":"SV-SS","postcode":"1102","country":"El Salvador","country_code":"sv"},"boundingbox":["13.7111604","13.7112604","-89.2077187","-89.2076187"]}