{"place_id":287064019,"licence":"Data © OpenStreetMap contributors, ODbL 1.0. http://osm.org/copyright","osm_type":"way","osm_id":700431998,"lat":"13.7802349","lon":"-89.1172394","category":"amenity","type":"fast_food","place_rank":30,"importance":6.725185015635947e-05,"addresstype":"amenity","name":"Don Pollo","display_name":"Don Pollo, Calle San Nicolás, Tonacatepeque, San Salvador Este, San Salvador, El Salvador","address":{"amenity":"Don Pollo","road":"Calle San Nicolás","town":"Tonacatepeque","municipality":"San Salvador Este","state":"San Salvador","ISO3166-2-lvl4":"SV-SS","country":"El Salvador","country_code":"sv"},"boundingbox":["13.7801879","13.7802818","-89.1172625","-89.1172165"]}