{"place_id":89376404,"licence":"Data © OpenStreetMap contributors, ODbL 1.0. http://osm.org/copyright","osm_type":"node","osm_id":1901202883,"lat":"48.8344837","lon":"2.2883046","category":"amenity","type":"dancing_school","place_rank":30,"importance":9.317235065227768e-05,"addresstype":"amenity","name":"Danse Cadix (Rock4You)","display_name":"Danse Cadix (Rock4You), 2, Rue de Cadix, Quartier Saint-Lambert, Paris 15e Arrondissement, Paris, France métropolitaine, 75015, France","address":{"amenity":"Danse Cadix (Rock4You)","house_number":"2","road":"Rue de Cadix","city_block":"Quartier Saint-Lambert","suburb":"Paris 15e Arrondissement","city_district":"Paris","city":"Paris","ISO3166-2-lvl6":"FR-75C","region":"France métropolitaine","postcode":"75015","country":"France","country_code":"fr"},"boundingbox":["48.8344337","48.8345337","2.2882546","2.2883546"]}