{"place_id":16101522,"licence":"Data © OpenStreetMap contributors, ODbL 1.0. http://osm.org/copyright","osm_type":"node","osm_id":11374843861,"lat":"-34.5767859","lon":"-58.4340993","category":"amenity","type":"restaurant","place_rank":30,"importance":8.279926756690345e-05,"addresstype":"amenity","name":"Ganesha - Arts & Pizza","display_name":"Ganesha - Arts & Pizza, 5519, Paraguay, Palermo Hollywood, Palermo, Buenos Aires, Comuna 14, Ciudad Autónoma de Buenos Aires, C1425BTK, Argentina","address":{"amenity":"Ganesha - Arts & Pizza","house_number":"5519","road":"Paraguay","neighbourhood":"Palermo Hollywood","suburb":"Palermo","city":"Buenos Aires","state_district":"Comuna 14","state":"Ciudad Autónoma de Buenos Aires","ISO3166-2-lvl4":"AR-C","postcode":"C1425BTK","country":"Argentina","country_code":"ar"},"boundingbox":["-34.5768359","-34.5767359","-58.4341493","-58.4340493"]}