{"place_id":16184330,"licence":"Data © OpenStreetMap contributors, ODbL 1.0. http://osm.org/copyright","osm_type":"node","osm_id":11260033707,"lat":"-34.6107910","lon":"-58.3802297","category":"office","type":"estate_agent","place_rank":30,"importance":8.279926756690345e-05,"addresstype":"office","name":"Jacaranda Rentals","display_name":"Jacaranda Rentals, Adolfo Alsina, Monserrat, Buenos Aires, Comuna 1, Ciudad Autónoma de Buenos Aires, C1091AAQ, Argentina","address":{"office":"Jacaranda Rentals","road":"Adolfo Alsina","suburb":"Monserrat","city":"Buenos Aires","state_district":"Comuna 1","state":"Ciudad Autónoma de Buenos Aires","ISO3166-2-lvl4":"AR-C","postcode":"C1091AAQ","country":"Argentina","country_code":"ar"},"boundingbox":["-34.6108410","-34.6107410","-58.3802797","-58.3801797"]}